<?xml version="1.0" encoding="UTF-8" standalone="no"?>
<opendata dataType="L" lastModified="2026/04/03 15:30:49" mailCount="50" odType="02">
    <mail>
        <keyCd>164108</keyCd>
        <infoType>R10</infoType>
        <leaveDate>2026/04/03 15:20:40</leaveDate>
        <area>
            <cd>42</cd>
        </area>
        <country areaCd="42">
            <cd>0994</cd>
        </country>
        <title>領事窓口の一時閉鎖のお知らせについて</title>
        <lead>中東情勢の緊迫化等の影響を受け、在アゼルバイジャン日本国大使館の領事窓口は、来訪者の安全のため、引き続き４月６日（月）から４月１０日（金）まで一時的に閉鎖します。
　緊急時には、末尾に記載の【問い合わせ先】への連絡をお願い致します。
     【問い合わせ先】
　　在アゼルバイジャン日本国大使館
　　Tel:+944 50 222 8063
　　Email: consular@bk.mofa.go.jp</lead>
        <infoUrl>https://www.anzen.mofa.go.jp/od/ryojiMailDetail.html?keyCd=164108</infoUrl>
        <xmlAllUrl>https://www.ezairyu.mofa.go.jp/opendata/mail/164108A.xml</xmlAllUrl>
        <xmlNormalUrl>https://www.ezairyu.mofa.go.jp/opendata/mail/164108.xml</xmlNormalUrl>
        <xmlLightUrl>https://www.ezairyu.mofa.go.jp/opendata/mail/164108L.xml</xmlLightUrl>
        <koukanCd>530A</koukanCd>
    </mail>
    <mail>
        <keyCd>164107</keyCd>
        <infoType>R10</infoType>
        <leaveDate>2026/04/03 14:30:40</leaveDate>
        <area>
            <cd>10</cd>
        </area>
        <country areaCd="10">
            <cd>0092</cd>
        </country>
        <title>カラチ市内における抗議活動に関する注意喚起</title>
        <lead>本日（４月３日）、カラチ市内において、ガソリン等の燃料の値上げに対する抗議活動が予定されているため、最新の情報取得に努め、混雑している場所には近づかないようにしてください。</lead>
        <infoUrl>https://www.anzen.mofa.go.jp/od/ryojiMailDetail.html?keyCd=164107</infoUrl>
        <xmlAllUrl>https://www.ezairyu.mofa.go.jp/opendata/mail/164107A.xml</xmlAllUrl>
        <xmlNormalUrl>https://www.ezairyu.mofa.go.jp/opendata/mail/164107.xml</xmlNormalUrl>
        <xmlLightUrl>https://www.ezairyu.mofa.go.jp/opendata/mail/164107L.xml</xmlLightUrl>
        <koukanCd>610E</koukanCd>
    </mail>
    <mail>
        <keyCd>164105</keyCd>
        <infoType>R10</infoType>
        <leaveDate>2026/04/03 09:00:42</leaveDate>
        <area>
            <cd>42</cd>
        </area>
        <country areaCd="42">
            <cd>9007</cd>
        </country>
        <title>宗教関連イベントにおけるテロに関する注意喚起</title>
        <lead>●宗教に関連した祝祭日やイベントでは、人の集まりや移動が増えるため、無差別テロに遭遇する可能性が高まります。特に現在、中東情勢が悪化しており、中東地域以外でも、不測の事態が発生する可能性は排除されません。  
●４月１日（水）から約１週間、ユダヤ教の過越祭（ペサハ）が予定されているほか、４月１２日（日）にはロシア正教会の復活祭（カトリック・プロテスタントでは４月５日（日））が予定されています。  
●常に最新情報の入手に努め、安全確保に十分注意を払ってください。</lead>
        <infoUrl>https://www.anzen.mofa.go.jp/od/ryojiMailDetail.html?keyCd=164105</infoUrl>
        <xmlAllUrl>https://www.ezairyu.mofa.go.jp/opendata/mail/164105A.xml</xmlAllUrl>
        <xmlNormalUrl>https://www.ezairyu.mofa.go.jp/opendata/mail/164105.xml</xmlNormalUrl>
        <xmlLightUrl>https://www.ezairyu.mofa.go.jp/opendata/mail/164105L.xml</xmlLightUrl>
        <koukanCd>517V</koukanCd>
    </mail>
    <mail>
        <keyCd>164104</keyCd>
        <infoType>R10</infoType>
        <leaveDate>2026/04/03 08:35:40</leaveDate>
        <area>
            <cd>42</cd>
        </area>
        <country areaCd="42">
            <cd>9007</cd>
        </country>
        <title>宗教関連イベントにおけるテロに関する注意喚起</title>
        <lead>●宗教に関連した祝祭日やイベントでは、人の集まりや移動が増えるため、無差別テロに遭遇する可能性が高まります。特に現在、中東情勢が悪化しており、中東地域以外でも、不測の事態が発生する可能性は排除されません。  
●４月１日（水）から約１週間、ユダヤ教の過越祭（ペサハ）が予定されているほか、４月１２日（日）にはロシア正教会の復活祭（キリスト教では４月５日（日））が予定されています。  
●常に最新情報の入手に努め、安全確保に十分注意を払ってください。</lead>
        <infoUrl>https://www.anzen.mofa.go.jp/od/ryojiMailDetail.html?keyCd=164104</infoUrl>
        <xmlAllUrl>https://www.ezairyu.mofa.go.jp/opendata/mail/164104A.xml</xmlAllUrl>
        <xmlNormalUrl>https://www.ezairyu.mofa.go.jp/opendata/mail/164104.xml</xmlNormalUrl>
        <xmlLightUrl>https://www.ezairyu.mofa.go.jp/opendata/mail/164104L.xml</xmlLightUrl>
        <koukanCd>517E</koukanCd>
    </mail>
    <mail>
        <keyCd>164103</keyCd>
        <infoType>R10</infoType>
        <leaveDate>2026/04/03 03:10:41</leaveDate>
        <area>
            <cd>50</cd>
        </area>
        <country areaCd="50">
            <cd>0973</cd>
        </country>
        <title>キング・ファハド・コーズウェイへの脅威情報(４月２日）</title>
        <lead>１．４月２日(現地時間)、イランのイスラム革命防衛隊（IRGC）の機関であるファールス通信は、キャラジB1橋への空爆に対する報復としてクウェート、サウジアラビア、アブダビ、ヨルダンにある複数の橋をイラン軍の攻撃目標候補として挙げました。

２．攻撃目標として挙げた橋には、サウジアラビアとバーレーンを結ぶキング・ファハド・コーズウェイも含まれています。同道路を利用してサウジアラビアへ出国する際は、夜間や混雑時の利用を避けるとともに、ウェブサイト（ https://kfca.sa/en/ ）から最新の状況を確認するなど情報収集に努めてください。

３．また、ドローンやミサイル等に起因すると思われる爆発音等が聞こえた場合は、決して近づくことなく、
屋外にいる場合：近くの建物や地下への避難、物陰に身を隠す
屋内にいる場合：窓から離れる、窓のない部屋に移動する
といった、ご自身の身を守る行動を最優先に行うようお願いします。</lead>
        <infoUrl>https://www.anzen.mofa.go.jp/od/ryojiMailDetail.html?keyCd=164103</infoUrl>
        <xmlAllUrl>https://www.ezairyu.mofa.go.jp/opendata/mail/164103A.xml</xmlAllUrl>
        <xmlNormalUrl>https://www.ezairyu.mofa.go.jp/opendata/mail/164103.xml</xmlNormalUrl>
        <xmlLightUrl>https://www.ezairyu.mofa.go.jp/opendata/mail/164103L.xml</xmlLightUrl>
        <koukanCd>727A</koukanCd>
    </mail>
    <mail>
        <keyCd>164102</keyCd>
        <infoType>R10</infoType>
        <leaveDate>2026/04/03 01:25:41</leaveDate>
        <area>
            <cd>60</cd>
        </area>
        <country areaCd="60">
            <cd>0254</cd>
        </country>
        <country areaCd="60">
            <cd>0252</cd>
        </country>
        <title>宗教関連イベント期間等におけるテロに関する注意喚起</title>
        <lead>●宗教に関連した祝祭日やイベントでは、人の集まりや移動が増えるため、テロの標的とされる可能性が高まります。特に現在、中東情勢の悪化を受け、中東地域以外でも不測の事態が発生する可能性は排除できません。

●４月１日（水）から約１週間、ユダヤ教の過越祭（ペサハ）が予定されているほか、４月５日（日）にはキリスト教の復活祭（イースター）が予定されています。

●近年、警備や監視が手薄で、一般市民が多く集まる場所（ソフトターゲット）を標的としたテロが発生しています。常に最新情報の入手に努め、安全確保に十分注意を払うとともに、テロの被害に遭う可能性を減らすため、以下の対策をお願いいたします。 
（１）	次の場所がテロの標的となりやすいことを十分認識しておく
観光施設、観光地周辺の道路、祝祭日、イベント等の会場、レストラン、ホテル、ショッピングモール、ナイトクラブ、映画館、公共交通機関、宗教関連施設等人が多く集まる施設、政府関連施設（特に軍、警察、治安関連施設）等
（２）上記（１）の場所を訪れる際には、周囲の状況に注意を払い、不審な人物や状況を察知したら速やかにその場を離れる、できるだけ滞在時間を短くする等の注意の気持ちを持ち、その場の状況に応じた安全確保に十分注意を払う
（３）もし、現地当局の指示があればそれに従う。特にテロに遭遇してしまった場合には、警察官等の指示をよく聞き冷静に行動するように努める</lead>
        <infoUrl>https://www.anzen.mofa.go.jp/od/ryojiMailDetail.html?keyCd=164102</infoUrl>
        <xmlAllUrl>https://www.ezairyu.mofa.go.jp/opendata/mail/164102A.xml</xmlAllUrl>
        <xmlNormalUrl>https://www.ezairyu.mofa.go.jp/opendata/mail/164102.xml</xmlNormalUrl>
        <xmlLightUrl>https://www.ezairyu.mofa.go.jp/opendata/mail/164102L.xml</xmlLightUrl>
        <koukanCd>713A</koukanCd>
    </mail>
    <mail>
        <keyCd>164099</keyCd>
        <infoType>R10</infoType>
        <leaveDate>2026/04/03 00:05:40</leaveDate>
        <area>
            <cd>50</cd>
        </area>
        <country areaCd="50">
            <cd>0965</cd>
        </country>
        <title>クウェート国際空港の状況（4月2日18:00時点）について</title>
        <lead>○4月2日18:00時点（現地時間）、クウェート国際空港は閉鎖されています。
邦人の皆様におかれましても、関連情報の入手に努めるようお願いします。

○同空港のサイトを以下のとおりお知らせします。
クウェート国際空港（Kuwait International Airport）
https://www.kuwaitairport.gov.kw/en/　
※	クウェート発着便の運行状況について確認できます。

○今後、同空港が再開される等の変更がありましたら、改めてお知らせします。


在クウェート日本国大使館
当館公式サイト： https://www.kw.emb-japan.go.jp/itprtop_ja/index.html
メールアドレス： consular@kw.mofa.go.jp 
電話：（+965）2530-9400

※「在留届」を提出された方で、既に日本に帰国又は他国に転出された方は、以下のURLから「変更届・帰国届」の提出をお願いいたします。
（ https://www.ezairyu.mofa.go.jp/RRnet/index.html ）
※「たびレジ」簡易登録をされた方でメールの配信を停止したい方は、以下のURLから停止手続きをお願い致します。
（ https://www.ezairyu.mofa.go.jp/tabireg/simple/delete ）
※このメールは在留届、たびレジに登録されたメールアドレスに配信されております。
災害や騒乱等が発生した際、ご家族、ご友人、同僚の方を守るため、一人でも多くの方に安全対策に関する情報が届くよう、「在留届」（３か月以上の滞在）または「たびレジ」（３か月未満の滞在）の登録を、お知り合いの方や出張者、旅行者の方にご案内いただけますようお願いいたします。</lead>
        <infoUrl>https://www.anzen.mofa.go.jp/od/ryojiMailDetail.html?keyCd=164099</infoUrl>
        <xmlAllUrl>https://www.ezairyu.mofa.go.jp/opendata/mail/164099A.xml</xmlAllUrl>
        <xmlNormalUrl>https://www.ezairyu.mofa.go.jp/opendata/mail/164099.xml</xmlNormalUrl>
        <xmlLightUrl>https://www.ezairyu.mofa.go.jp/opendata/mail/164099L.xml</xmlLightUrl>
        <koukanCd>706A</koukanCd>
    </mail>
    <mail>
        <keyCd>164098</keyCd>
        <infoType>R10</infoType>
        <leaveDate>2026/04/02 23:55:40</leaveDate>
        <area>
            <cd>50</cd>
        </area>
        <country areaCd="50">
            <cd>0973</cd>
        </country>
        <title>バーレーン国際空港及びキング・ファハド・コーズウェイの状況（４月２日　１８：００現在）</title>
        <lead>○ バーレーン国際空港は、引き続きバーレーンの空域が閉鎖されているため、バーレーン国際空港における離発着は行われていません。同空港が再開される等の情報がありましたら、改めてメールや当館ホームページでお知らせします。
○ ダンマン空港におけるガルフエアの運航便について、新たにイスタンブール（トルコ）、アテネ（ギリシャ）、ティルヴァナンタプラム（インド）とダンマン間の運航が追加されました。
○ 深夜帯の緊急警報システムの運用が４月１日から変更されました。</lead>
        <infoUrl>https://www.anzen.mofa.go.jp/od/ryojiMailDetail.html?keyCd=164098</infoUrl>
        <xmlAllUrl>https://www.ezairyu.mofa.go.jp/opendata/mail/164098A.xml</xmlAllUrl>
        <xmlNormalUrl>https://www.ezairyu.mofa.go.jp/opendata/mail/164098.xml</xmlNormalUrl>
        <xmlLightUrl>https://www.ezairyu.mofa.go.jp/opendata/mail/164098L.xml</xmlLightUrl>
        <koukanCd>727A</koukanCd>
    </mail>
    <mail>
        <keyCd>164097</keyCd>
        <infoType>R10</infoType>
        <leaveDate>2026/04/02 23:45:41</leaveDate>
        <area>
            <cd>42</cd>
        </area>
        <country areaCd="42">
            <cd>9007</cd>
        </country>
        <title>宗教関連イベントにおけるテロに関する注意事項</title>
        <lead>●宗教に関連した祝祭日やイベントでは、人の集まりや移動が増えるため、無差別テロに遭遇する可能性が高まります。特に現在、中東情勢が悪化しており、中東地域以外でも、不測の事態が発生する可能性は排除されません。  
●４月１日（水）から約１週間、ユダヤ教の過越祭（ペサハ）が予定されているほか、４月１２日（日）にはロシア正教会の復活祭（キリスト教では４月５日（日））が予定されています。  
●常に最新情報の入手に努め、安全確保に十分注意を払ってください。

１ 宗教に関連した祝祭日やイベントは、人の集まりや移動が増えるため、無差別テロに遭遇する可能性が高まります。現在、中東情勢が悪化しており、中東地域以外でも、不測の事態が発生する可能性は排除されません。

２ 近年、警備や監視が手薄で、一般市民が多く集まる場所（ソフトターゲット）を標的としたテロが各国で発生していますが、これらは組織とのつながりが薄い単独犯による場合が多く、事前の取締りが難しいため、こうしたテロの発生が今後も継続することが懸念されます。  

３ ４月１日（水）から約１週間、ユダヤ教の過越祭（ペサハ）が予定されているほか、４月１２日にはロシア正教会の復活祭（キリスト教では４月５日（日））が予定されています。 

４ ついては、外務省が発出した以下の「広域情報」を御参照の上、テロの被害に遭うことのないよう十分御注意願います。  
２０２６年２月１３日付外務省「広域情報」：
https://www.anzen.mofa.go.jp/info/pcwideareaspecificinfo_2026C012.html

５ 万一被害に遭った場合や邦人の被害を認知した場合は、警察に通報し対応を依頼するとともに、安全な場所に避難した後、当館まで御一報ください。</lead>
        <infoUrl>https://www.anzen.mofa.go.jp/od/ryojiMailDetail.html?keyCd=164097</infoUrl>
        <xmlAllUrl>https://www.ezairyu.mofa.go.jp/opendata/mail/164097A.xml</xmlAllUrl>
        <xmlNormalUrl>https://www.ezairyu.mofa.go.jp/opendata/mail/164097.xml</xmlNormalUrl>
        <xmlLightUrl>https://www.ezairyu.mofa.go.jp/opendata/mail/164097L.xml</xmlLightUrl>
        <koukanCd>517F</koukanCd>
    </mail>
    <mail>
        <keyCd>164096</keyCd>
        <infoType>R10</infoType>
        <leaveDate>2026/04/02 22:10:40</leaveDate>
        <area>
            <cd>42</cd>
        </area>
        <country areaCd="42">
            <cd>9007</cd>
        </country>
        <title>宗教関連イベントにおけるテロに関する注意喚起</title>
        <lead>●宗教に関連した祝祭日やイベントでは、人の集まりや移動が増えるため、無差別テロに遭遇する可能性が高まります。特に現在、中東情勢が悪化しており、中東地域以外でも、不測の事態が発生する可能性は排除されません。  
●４月１日（水）から約１週間、ユダヤ教の過越祭（ペサハ）が予定されているほか、４月１２日（日）にはロシア正教会の復活祭（キリスト教では４月５日（日））が予定されています。  
●常に最新情報の入手に努め、安全確保に十分注意を払ってください。</lead>
        <infoUrl>https://www.anzen.mofa.go.jp/od/ryojiMailDetail.html?keyCd=164096</infoUrl>
        <xmlAllUrl>https://www.ezairyu.mofa.go.jp/opendata/mail/164096A.xml</xmlAllUrl>
        <xmlNormalUrl>https://www.ezairyu.mofa.go.jp/opendata/mail/164096.xml</xmlNormalUrl>
        <xmlLightUrl>https://www.ezairyu.mofa.go.jp/opendata/mail/164096L.xml</xmlLightUrl>
        <koukanCd>517A</koukanCd>
    </mail>
    <mail>
        <keyCd>164093</keyCd>
        <infoType>R10</infoType>
        <leaveDate>2026/04/02 18:35:41</leaveDate>
        <area>
            <cd>50</cd>
        </area>
        <country areaCd="50">
            <cd>0968</cd>
        </country>
        <title>米国関連企業への脅威情報（４月２日）</title>
        <lead>1. イランのイスラム革命防衛隊（IRGC）は、「イランへの攻撃において主要な役割を果たしている米国のICT及びAI企業を標的にする。」と宣言し、地域内の関連企業の従業員及び周辺住民は半径１キロメートル以内からの避難を呼びかけ、「今後イラン国内で暗殺行為が発生した場合、4月1日以降当該企業は攻撃され得る。」として、関連企業としてCisco、Oracle、GE等18の企業を名指ししました。
（関連リンク：ペルシャ語）：https://t.me/sepahpasdaran/20555 
 
2. 本声明内容を踏まえ、当面の間、関連する可能性のある施設への、不要不急の立ち寄りは避けるようにしてください。

3. ドローンやミサイル等に起因すると思われる爆発音等が聞こえた場合には、決して興味本位で近づくことなく、
屋外にいる場合：　近くの建物や地下への避難、物陰に身を隠す
屋内にいる場合：　窓から離れる、窓のない部屋に移動する
といった、ご自身の身を守る行動を最優先に行うようお願いします。

4. また、オマーン当局は、軍事・治安関連の画像・動画の公開や未確認情報のSNS等での拡散を控えるよう警告していますので、そうした行為には厳に控えてください。</lead>
        <infoUrl>https://www.anzen.mofa.go.jp/od/ryojiMailDetail.html?keyCd=164093</infoUrl>
        <xmlAllUrl>https://www.ezairyu.mofa.go.jp/opendata/mail/164093A.xml</xmlAllUrl>
        <xmlNormalUrl>https://www.ezairyu.mofa.go.jp/opendata/mail/164093.xml</xmlNormalUrl>
        <xmlLightUrl>https://www.ezairyu.mofa.go.jp/opendata/mail/164093L.xml</xmlLightUrl>
        <koukanCd>761A</koukanCd>
    </mail>
    <mail>
        <keyCd>164092</keyCd>
        <infoType>R10</infoType>
        <leaveDate>2026/04/02 18:15:43</leaveDate>
        <area>
            <cd>50</cd>
        </area>
        <country areaCd="50">
            <cd>0972</cd>
        </country>
        <country areaCd="50">
            <cd>0970</cd>
        </country>
        <title>テルアビブ（ベン・グリオン）空港等の状況について（4月2日(木)12:00時点）</title>
        <lead>・4月2日(木)12時現在（現地時間）、テルアビブ（ベン・グリオン）空港は、便数・搭乗者数を制限した状態での極めて限定された運用となっています。 
・イスラエル系航空会社のみによる特別運航（Recovery/Rescue/Emergency Flight）が継続しています。
・3月23日(月)17時から、１時間あたり出発機１機、到着機１機の制限及びイスラエル出発便搭乗可能人数が50人となっています。
・エル・アルの定期便は、4月11日(土)までキャンセルされています。
・本日、「4月6日(月)出発便フライト予定」追加

==============================
◆イラン、ヒズボッラーからのミサイル等に 
　よる攻撃が継続しています。  
◆在留邦人・渡航者の方で、負傷等の被害に 
　遭われた方や被害の情報に接した方がいらっ
　しゃいましたら、下記の当館連絡先まで 
　ご連絡をお願いします。 
==============================

▲▼▲▼▲▼新着情報▲▼▲▼▲▼ 

■■ベン・グリオン空港運航状況 
●公式ウェブページ（出発便情報） 
https://www.iaa.gov.il/en/airports/ben-gurion/flight-board/?flightType=departures　
※掲載されているのは4月6日(月)まで（本日、「4月6日分フライト予定」追加）。

●4月2日(木)出発便フライト予定（22便）
AIR HAIFA&lt;3&gt;
----LARNACA 3
ARKIA ISRAELI AIRLINES&lt;8&gt;
----ATHENS 4
----LARNACA 3
----LARNACA via BANGKOK 1
ISRAIR AIRLINES&lt;11&gt;
----ATHENS 3
----LARNACA 3
----ROME    3
----FRANKFURT    1
----TBILISI    1</lead>
        <infoUrl>https://www.anzen.mofa.go.jp/od/ryojiMailDetail.html?keyCd=164092</infoUrl>
        <xmlAllUrl>https://www.ezairyu.mofa.go.jp/opendata/mail/164092A.xml</xmlAllUrl>
        <xmlNormalUrl>https://www.ezairyu.mofa.go.jp/opendata/mail/164092.xml</xmlNormalUrl>
        <xmlLightUrl>https://www.ezairyu.mofa.go.jp/opendata/mail/164092L.xml</xmlLightUrl>
        <koukanCd>705A</koukanCd>
    </mail>
    <mail>
        <keyCd>164090</keyCd>
        <infoType>R10</infoType>
        <leaveDate>2026/04/02 16:50:41</leaveDate>
        <area>
            <cd>42</cd>
        </area>
        <country areaCd="42">
            <cd>0371</cd>
        </country>
        <title>宗教関連イベント期間等におけるテロに関する注意喚起</title>
        <lead>（ポイント）
●宗教に関連した祝祭日やイベントでは、人の集まりや移動が増えるため、テロの標的とされる可能性が高まります。特に現在、中東情勢が悪化しており、中東地域以外でも、不測の事態が発生する可能性は排除されません。  
●４月１日（水）から約１週間、ユダヤ教の過越祭（ペサハ）が予定されているほか、４月５日（日）にはキリスト教の復活祭（イースター）が予定されています。  
●常に最新情報の入手に努め、安全確保に十分注意を払ってください。</lead>
        <infoUrl>https://www.anzen.mofa.go.jp/od/ryojiMailDetail.html?keyCd=164090</infoUrl>
        <xmlAllUrl>https://www.ezairyu.mofa.go.jp/opendata/mail/164090A.xml</xmlAllUrl>
        <xmlNormalUrl>https://www.ezairyu.mofa.go.jp/opendata/mail/164090.xml</xmlNormalUrl>
        <xmlLightUrl>https://www.ezairyu.mofa.go.jp/opendata/mail/164090L.xml</xmlLightUrl>
        <koukanCd>528A</koukanCd>
    </mail>
    <mail>
        <keyCd>164089</keyCd>
        <infoType>R10</infoType>
        <leaveDate>2026/04/02 14:30:42</leaveDate>
        <area>
            <cd>50</cd>
        </area>
        <country areaCd="50">
            <cd>0971</cd>
        </country>
        <title>イランからの攻撃に伴う注意喚起（４月２日 ９時３０分）</title>
        <lead>○本日、ドバイ国際空港（DXB）では、成田行きの便は運航され、すでに出発しましたが、羽田行きの便は欠航となっています。今後の運航につきましては、空港・航空会社のホームページ等をご確認ください。 
https://dubaiairports.ae/　（ドバイ国際空港HP）   
https://www.emirates.com/ae/english/　（エミレーツ航空HP）</lead>
        <infoUrl>https://www.anzen.mofa.go.jp/od/ryojiMailDetail.html?keyCd=164089</infoUrl>
        <xmlAllUrl>https://www.ezairyu.mofa.go.jp/opendata/mail/164089A.xml</xmlAllUrl>
        <xmlNormalUrl>https://www.ezairyu.mofa.go.jp/opendata/mail/164089.xml</xmlNormalUrl>
        <xmlLightUrl>https://www.ezairyu.mofa.go.jp/opendata/mail/164089L.xml</xmlLightUrl>
        <koukanCd>755D</koukanCd>
    </mail>
    <mail>
        <keyCd>164088</keyCd>
        <infoType>R10</infoType>
        <leaveDate>2026/04/02 12:40:41</leaveDate>
        <title>【津波情報】米国津波センター発表（津波予想解除）</title>
        <lead>本日午前にお知らせした津波予想は解除されました。</lead>
        <infoUrl>https://www.anzen.mofa.go.jp/od/ryojiMailDetail.html?keyCd=164088</infoUrl>
        <xmlAllUrl>https://www.ezairyu.mofa.go.jp/opendata/mail/164088A.xml</xmlAllUrl>
        <xmlNormalUrl>https://www.ezairyu.mofa.go.jp/opendata/mail/164088.xml</xmlNormalUrl>
        <xmlLightUrl>https://www.ezairyu.mofa.go.jp/opendata/mail/164088L.xml</xmlLightUrl>
        <koukanCd>067C</koukanCd>
    </mail>
    <mail>
        <keyCd>164087</keyCd>
        <infoType>R10</infoType>
        <leaveDate>2026/04/02 10:50:42</leaveDate>
        <area>
            <cd>10</cd>
        </area>
        <country areaCd="10">
            <cd>0886</cd>
        </country>
        <title>清明節等期間中の閉所日及び安全対策に関するお知らせ</title>
        <lead>●台湾の清明節等の祝日に合わせ、当協会台北事務所及び高雄事務所は、４月３日（金）から４月６日（月）まで閉所となります。４月７日（火）より開所します。
●清明節期間中は、多くの人が移動し、特に観光地等は大勢の人が集まることが見込まれます。貴重品・旅券（パスポート）等の管理含め、外出の際には周囲の状況にくれぐれも留意し、可能な限りの安全対策に努めてください。また、渡航にあたっては、十分な補償内容の海外旅行保険等に加入することを強く推奨します。
●出入境時の持ち出し・持ち込みに制限のある物品もありますので、ご留意ください。また、感染症にご注意ください。</lead>
        <infoUrl>https://www.anzen.mofa.go.jp/od/ryojiMailDetail.html?keyCd=164087</infoUrl>
        <xmlAllUrl>https://www.ezairyu.mofa.go.jp/opendata/mail/164087A.xml</xmlAllUrl>
        <xmlNormalUrl>https://www.ezairyu.mofa.go.jp/opendata/mail/164087.xml</xmlNormalUrl>
        <xmlLightUrl>https://www.ezairyu.mofa.go.jp/opendata/mail/164087L.xml</xmlLightUrl>
        <koukanCd>632B</koukanCd>
    </mail>
    <mail>
        <keyCd>164086</keyCd>
        <infoType>R10</infoType>
        <leaveDate>2026/04/02 10:20:40</leaveDate>
        <area>
            <cd>20</cd>
        </area>
        <country areaCd="20">
            <cd>0691</cd>
        </country>
        <title>ヤップ州に対する津波警報の注意喚起の発出</title>
        <lead>●ヤップ州に津波に対する注意喚起が発出されました

本日４月２日ヤップ州時刻午前8時48分、インドンシア北スラウェシ州の東沖海底62キロを震源とするマグニチュード7.6の地震が発生しました。地震に伴って、米国津波センターは、ヤップ州を津波警報地域に指定致しました。情報収集するとともに、同地域に滞在中の皆様におかれましては、海岸には極力近づかないなどご注意下さい。

●万一、被害にあった方または被害にあった方を認知した場合には、大使館までご連絡願います。

ＮＯＡＡ：　https://www.tsunami.gov/
警報内容：
https://www.tsunami.gov/events/PHEB/2026/04/01/26091003/6/WEPA40/WEPA40.txt

在ミクロネシア日本大使館
電話：（６９１）３２０－５４６５ 
E-mail：japanemb-consul@pi.mofa.jp 
ＨＰ: https://www.micronesia.emb-japan.go.jp/itprtop_ja/index.html 
ＦＢ: https://www.facebook.com/embassyofjapaninfsm/

※「たびレジ」に簡易登録された方でメールの配信を変更・停止したい方は、以下のURLから手続きをお願いいたします。
（変更）https://www.ezairyu.mofa.go.jp/tabireg/simple/auth
（停止）https://www.ezairyu.mofa.go.jp/tabireg/simple/delete</lead>
        <infoUrl>https://www.anzen.mofa.go.jp/od/ryojiMailDetail.html?keyCd=164086</infoUrl>
        <xmlAllUrl>https://www.ezairyu.mofa.go.jp/opendata/mail/164086A.xml</xmlAllUrl>
        <xmlNormalUrl>https://www.ezairyu.mofa.go.jp/opendata/mail/164086.xml</xmlNormalUrl>
        <xmlLightUrl>https://www.ezairyu.mofa.go.jp/opendata/mail/164086L.xml</xmlLightUrl>
        <koukanCd>627A</koukanCd>
    </mail>
    <mail>
        <keyCd>164085</keyCd>
        <infoType>R10</infoType>
        <leaveDate>2026/04/02 09:55:57</leaveDate>
        <title>【津波情報】米国津波センター発表</title>
        <lead>米国津波センターにより北マリアナ諸島を含む地域に津波予想が発表されましたので（北マリアナ諸島沿岸では30cm以下の予想）、海岸付近での行動には十分にご注意下さい。</lead>
        <infoUrl>https://www.anzen.mofa.go.jp/od/ryojiMailDetail.html?keyCd=164085</infoUrl>
        <xmlAllUrl>https://www.ezairyu.mofa.go.jp/opendata/mail/164085A.xml</xmlAllUrl>
        <xmlNormalUrl>https://www.ezairyu.mofa.go.jp/opendata/mail/164085.xml</xmlNormalUrl>
        <xmlLightUrl>https://www.ezairyu.mofa.go.jp/opendata/mail/164085L.xml</xmlLightUrl>
        <koukanCd>067C</koukanCd>
    </mail>
    <mail>
        <keyCd>164084</keyCd>
        <infoType>R10</infoType>
        <leaveDate>2026/04/02 09:55:56</leaveDate>
        <area>
            <cd>10</cd>
        </area>
        <country areaCd="10">
            <cd>0062</cd>
        </country>
        <title>【津波注意】北スラウェシ州ビトゥン沖での地震の発生</title>
        <lead>●4月2日6時48分(中部インドネシア時間) 北スラウェシ州のビトゥン沖（南東方向129km）を震源（震源の深さは62Km）としたM7.6の地震発生を受け、インドネシア気象庁は北スラウェシ州に津波注意報を発報しております。</lead>
        <infoUrl>https://www.anzen.mofa.go.jp/od/ryojiMailDetail.html?keyCd=164084</infoUrl>
        <xmlAllUrl>https://www.ezairyu.mofa.go.jp/opendata/mail/164084A.xml</xmlAllUrl>
        <xmlNormalUrl>https://www.ezairyu.mofa.go.jp/opendata/mail/164084.xml</xmlNormalUrl>
        <xmlLightUrl>https://www.ezairyu.mofa.go.jp/opendata/mail/164084L.xml</xmlLightUrl>
        <koukanCd>607X</koukanCd>
    </mail>
    <mail>
        <keyCd>164083</keyCd>
        <infoType>R20</infoType>
        <leaveDate>2026/04/02 09:51:21</leaveDate>
        <area>
            <cd>10</cd>
        </area>
        <country areaCd="10">
            <cd>0062</cd>
        </country>
        <title>スラウェシ州東沖におけるマグニチュード7.6の地震の発生</title>
        <lead>●本日４月２日西部インドネシア時刻午前5時48分（中部インドネシア午前6時48分）北スラウェシ州の東沖海底62キロを震源とするマグニチュード7.6の地震が発生しました。地震に伴って津波警報が発令されたものの、当館管轄州（バリ州、NTB州、NTT州）には発令されていません。今後、警報の発令範囲は変更される可能性があるため、情報収集するとともに、海岸には極力近づかないなどご注意下さい。
●今後も地震の情報に注意し身の安全確保に努めてください。
インドネシア気象庁（BMKG）ホームページ:
https://www.bmkg.go.id
●万一、被害にあった方または被害にあった方を認知した場合には、総領事館ま
でご連絡願います。</lead>
        <infoUrl>https://www.anzen.mofa.go.jp/od/ryojiMailDetail.html?keyCd=164083</infoUrl>
        <xmlAllUrl>https://www.ezairyu.mofa.go.jp/opendata/mail/164083A.xml</xmlAllUrl>
        <xmlNormalUrl>https://www.ezairyu.mofa.go.jp/opendata/mail/164083.xml</xmlNormalUrl>
        <xmlLightUrl>https://www.ezairyu.mofa.go.jp/opendata/mail/164083L.xml</xmlLightUrl>
        <koukanCd>607F</koukanCd>
    </mail>
    <mail>
        <keyCd>164080</keyCd>
        <infoType>R10</infoType>
        <leaveDate>2026/04/02 06:10:40</leaveDate>
        <area>
            <cd>33</cd>
        </area>
        <country areaCd="33">
            <cd>0591</cd>
        </country>
        <title>注意喚起：サンタクルス-コチャバンバ間旧街道の通行について</title>
        <lead>●降雨により、3月28日夜にはサンタクルスーコチャバンバ間（旧街道）で再び土砂崩れが発生し、落石により死傷者が出て、道路が一時期閉鎖されました。
●道路復旧後、4月1日未明に再度発生した土砂崩れにより、ラ・アンゴストゥーラ-サマイパタ間の道路が再度閉鎖されています。
●また、洪水のため閉鎖されているサンロレンソ-サリナス間でも、車両通行止めが続いています。
●今後も、サンタクルスーコチャバンバ間(旧街道)では土砂崩れ等が発生するおそれがあるため、当面の間、同区間の不要不急のバスを含む車両による移動はできるだけ控えるようにしてください。
●また、今後も洪水等の恐れがありますので、河川周辺地域には近づかないようにしてください。</lead>
        <infoUrl>https://www.anzen.mofa.go.jp/od/ryojiMailDetail.html?keyCd=164080</infoUrl>
        <xmlAllUrl>https://www.ezairyu.mofa.go.jp/opendata/mail/164080A.xml</xmlAllUrl>
        <xmlNormalUrl>https://www.ezairyu.mofa.go.jp/opendata/mail/164080.xml</xmlNormalUrl>
        <xmlLightUrl>https://www.ezairyu.mofa.go.jp/opendata/mail/164080L.xml</xmlLightUrl>
        <koukanCd>002A</koukanCd>
    </mail>
    <mail>
        <keyCd>164079</keyCd>
        <infoType>R10</infoType>
        <leaveDate>2026/04/02 05:40:40</leaveDate>
        <area>
            <cd>42</cd>
        </area>
        <country areaCd="42">
            <cd>0421</cd>
        </country>
        <title>宗教関連イベント期間等におけるテロに関する注意喚起</title>
        <lead>●　宗教に関連した祝祭日やイベントでは、人の集まりや移動が増えるため、テロの標的とされる可能性が高まります。特に現在、中東情勢が悪化しており、中東地域以外でも、不測の事態が発生する可能性は排除されません。
●　4月1日（水）から約1週間、ユダヤ教の過越祭（ペサハ）が予定されているほか、4月5日（日）にはキリスト教のカトリックの復活祭（イースター）、4月12日（日）には東方正教会の復活祭が予定されています。
●　常に最新情報の入手に努め、安全確保に十分注意を払ってください。</lead>
        <infoUrl>https://www.anzen.mofa.go.jp/od/ryojiMailDetail.html?keyCd=164079</infoUrl>
        <xmlAllUrl>https://www.ezairyu.mofa.go.jp/opendata/mail/164079A.xml</xmlAllUrl>
        <xmlNormalUrl>https://www.ezairyu.mofa.go.jp/opendata/mail/164079.xml</xmlNormalUrl>
        <xmlLightUrl>https://www.ezairyu.mofa.go.jp/opendata/mail/164079L.xml</xmlLightUrl>
        <koukanCd>543A</koukanCd>
    </mail>
    <mail>
        <keyCd>164076</keyCd>
        <infoType>R10</infoType>
        <leaveDate>2026/04/02 02:00:40</leaveDate>
        <area>
            <cd>60</cd>
        </area>
        <country areaCd="60">
            <cd>0222</cd>
        </country>
        <title>【モーリタニア】都市部における夜間車両通行禁止の決定について</title>
        <lead>モーリタニア政府は、４月２日（木）から、都市部において午前０時から午前５時までの車両通行を禁止することを決定しました。
国営通信報道によれば、これは国際的な原油の供給不足に対処するための決定であり、資源を効率的に使用することを目的としたものです。また、生活必需サービス、自転車、歩行者は通行禁止の対象外であり、バイクによる配達サービスは継続されるとされています。
これにより、ヌアクショット市内では当面の間、前記時間帯における自家用自動車及びバイクの運転は禁止されますので、ご承知おきください。</lead>
        <infoUrl>https://www.anzen.mofa.go.jp/od/ryojiMailDetail.html?keyCd=164076</infoUrl>
        <xmlAllUrl>https://www.ezairyu.mofa.go.jp/opendata/mail/164076A.xml</xmlAllUrl>
        <xmlNormalUrl>https://www.ezairyu.mofa.go.jp/opendata/mail/164076.xml</xmlNormalUrl>
        <xmlLightUrl>https://www.ezairyu.mofa.go.jp/opendata/mail/164076L.xml</xmlLightUrl>
        <koukanCd>736A</koukanCd>
    </mail>
    <mail>
        <keyCd>164075</keyCd>
        <infoType>R10</infoType>
        <leaveDate>2026/04/02 01:30:40</leaveDate>
        <area>
            <cd>42</cd>
        </area>
        <country areaCd="42">
            <cd>0048</cd>
        </country>
        <title>【安全情報】宗教関連の祝祭日等におけるテロに関する注意喚起</title>
        <lead>１ 宗教に関連する祝祭日やイベントでは、人の集まりや移動が増えるため、不特定多数の市民を標的としたテロのリスクが高まります。また、現在、中東情勢が悪化しており、情勢に影響を受けた不測の事態が発生する可能性も否定できません。 

２ ４月１日（水）から約１週間、ユダヤ教の過越祭（ペサハ）が予定されているほか、４月５日（日）にはキリスト教のカトリックの復活祭（イースター）、４月１２日（日）には東方正教会の復活祭が予定されています。

３ 近年、警備や監視が手薄で、一般市民が多く集まる場所（ソフトターゲット）を標的としたテロが発生しています。これらは組織とのつながりが薄い単独犯による場合が多く、事前の取締りが難しいため、今後も継続することが懸念されます。  

４ ついては、外務省が発出した以下の「広域情報」をご参照の上、一層の安全対策にご留意ください。  
２０２６年２月１３日付外務省「広域情報」：
https://www.anzen.mofa.go.jp/info/pcwideareaspecificinfo_2026C012.html


【お問い合わせ先】 
在ポーランド日本国大使館　領事班 
☆電話：＋４８ ２２ ６９６ ５００５※開館時間のみ[09:00～12:30、13:30～17:00]。開館時間外に緊急を要する場合には大使館代表番号（+48 22 696 5000）へお掛けください（閉館時電話対応委嘱業者がまずは伺うことになります）。 
☆メール：cons@wr.mofa.go.jp  
☆ＨＰ：https://www.pl.emb-japan.go.jp/itpr_ja/ryouji.html

※災害や騒乱等が発生した際、ご家族、ご友人、同僚を守るため、一人でも多く
の方に安全対策に関する情報が届くよう、在留届（3か月以上の滞在）の届出、又はたびレジ（3か月未満の滞在）の登録を、お知り合いの方や出張者・旅行者にご案内いただきますようお願いいたします。

＜たびレジ＞
https://www.ezairyu.mofa.go.jp/tabireg/index.html
＜オンライン在留届＞
https://www.ezairyu.mofa.go.jp/RRnet/index.html</lead>
        <infoUrl>https://www.anzen.mofa.go.jp/od/ryojiMailDetail.html?keyCd=164075</infoUrl>
        <xmlAllUrl>https://www.ezairyu.mofa.go.jp/opendata/mail/164075A.xml</xmlAllUrl>
        <xmlNormalUrl>https://www.ezairyu.mofa.go.jp/opendata/mail/164075.xml</xmlNormalUrl>
        <xmlLightUrl>https://www.ezairyu.mofa.go.jp/opendata/mail/164075L.xml</xmlLightUrl>
        <koukanCd>512A</koukanCd>
    </mail>
    <mail>
        <keyCd>164074</keyCd>
        <infoType>R10</infoType>
        <leaveDate>2026/04/02 01:00:42</leaveDate>
        <area>
            <cd>42</cd>
        </area>
        <country areaCd="42">
            <cd>0049</cd>
        </country>
        <title>【安全情報】宗教関連イベント期間等におけるテロに関する注意喚起</title>
        <lead>宗教に関連した祝祭日やイベントでは、人の集まりや移動が増えるため、テロの標的とされる可能性が高まります。
特に現在、中東情勢が悪化しており、中東地域以外でも、不測の事態が発生する可能性は排除されません。

近年、警備や監視が手薄で、一般市民が多く集まる場所（ソフトターゲット）を標的としたテロが発生していますが、これらは組織とのつながりが薄い単独犯による場合が多く、事前の取締りが難しいため、今後も継続することが懸念されます。

４月１日（水）から約１週間、ユダヤ教の過越祭（ペサハ）が予定されているほか、４月５日（日）にはキリスト教の復活祭（イースター）が予定されています。  
常に最新情報の入手に努め、安全確保に十分注意を払ってください。</lead>
        <infoUrl>https://www.anzen.mofa.go.jp/od/ryojiMailDetail.html?keyCd=164074</infoUrl>
        <xmlAllUrl>https://www.ezairyu.mofa.go.jp/opendata/mail/164074A.xml</xmlAllUrl>
        <xmlNormalUrl>https://www.ezairyu.mofa.go.jp/opendata/mail/164074.xml</xmlNormalUrl>
        <xmlLightUrl>https://www.ezairyu.mofa.go.jp/opendata/mail/164074L.xml</xmlLightUrl>
        <koukanCd>506G</koukanCd>
    </mail>
    <mail>
        <keyCd>164072</keyCd>
        <infoType>R10</infoType>
        <leaveDate>2026/04/02 00:40:43</leaveDate>
        <title>宗教関連イベント期間等におけるテロに関する注意喚起</title>
        <lead>●宗教に関連した祝祭日やイベントでは、人の集まりや移動が増えるため、テロの標的とされる可能性が高まります。特に現在、中東情勢が悪化しており、中東地域以外でも、不測の事態が発生する可能性は排除されません。 
●４月１日（水）から約１週間、ユダヤ教の過越祭（ペサハ）が予定されているほか、４月５日（日）にはキリスト教の復活祭（イースター）が予定されています。 
●常に最新情報の入手に努め、安全確保に十分注意を払ってください。</lead>
        <infoUrl>https://www.anzen.mofa.go.jp/od/ryojiMailDetail.html?keyCd=164072</infoUrl>
        <xmlAllUrl>https://www.ezairyu.mofa.go.jp/opendata/mail/164072A.xml</xmlAllUrl>
        <xmlNormalUrl>https://www.ezairyu.mofa.go.jp/opendata/mail/164072.xml</xmlNormalUrl>
        <xmlLightUrl>https://www.ezairyu.mofa.go.jp/opendata/mail/164072L.xml</xmlLightUrl>
        <koukanCd>301W</koukanCd>
    </mail>
    <mail>
        <keyCd>164071</keyCd>
        <infoType>R10</infoType>
        <leaveDate>2026/04/02 00:25:41</leaveDate>
        <area>
            <cd>42</cd>
        </area>
        <country areaCd="42">
            <cd>0044</cd>
        </country>
        <title>宗教関連イベント期間のテロに関する注意喚起</title>
        <lead>　宗教に関連した祝祭日やイベントでは、人の集まりや移動が増えるため、テロの標的とされる可能性が高まります。特に現在、中東情勢の悪化を受け、中東地域以外でも不測の事態が発生する可能性は排除できません。

　４月１日（水）からは約１週間、ユダヤ教の過越祭（ペサハ）が予定されているほか、４月５日（日）にはキリスト教の復活祭（イースター）が予定されています。
 
　常に最新情報の入手に努め、安全確保に十分注意を払ってください。</lead>
        <infoUrl>https://www.anzen.mofa.go.jp/od/ryojiMailDetail.html?keyCd=164071</infoUrl>
        <xmlAllUrl>https://www.ezairyu.mofa.go.jp/opendata/mail/164071A.xml</xmlAllUrl>
        <xmlNormalUrl>https://www.ezairyu.mofa.go.jp/opendata/mail/164071.xml</xmlNormalUrl>
        <xmlLightUrl>https://www.ezairyu.mofa.go.jp/opendata/mail/164071L.xml</xmlLightUrl>
        <koukanCd>518E</koukanCd>
    </mail>
    <mail>
        <keyCd>164070</keyCd>
        <infoType>R10</infoType>
        <leaveDate>2026/04/02 00:15:42</leaveDate>
        <area>
            <cd>42</cd>
        </area>
        <country areaCd="42">
            <cd>0381</cd>
        </country>
        <country areaCd="42">
            <cd>0382</cd>
        </country>
        <title>最近のセルビア各地における衝突事案について</title>
        <lead>【ポイント】 
・最近、セルビア各地で暴力を伴う衝突事案が増加しています。 
・今後も散発的に同様の衝突事案が発生する可能性があることから、大規模な集会や警察との衝突を認知した場合は、なるべく近づかずに十分な距離を取ることを心がけて下さい。</lead>
        <infoUrl>https://www.anzen.mofa.go.jp/od/ryojiMailDetail.html?keyCd=164070</infoUrl>
        <xmlAllUrl>https://www.ezairyu.mofa.go.jp/opendata/mail/164070A.xml</xmlAllUrl>
        <xmlNormalUrl>https://www.ezairyu.mofa.go.jp/opendata/mail/164070.xml</xmlNormalUrl>
        <xmlLightUrl>https://www.ezairyu.mofa.go.jp/opendata/mail/164070L.xml</xmlLightUrl>
        <koukanCd>520A</koukanCd>
    </mail>
    <mail>
        <keyCd>164069</keyCd>
        <infoType>R10</infoType>
        <leaveDate>2026/04/01 23:55:41</leaveDate>
        <area>
            <cd>42</cd>
        </area>
        <country areaCd="42">
            <cd>0420</cd>
        </country>
        <title>宗教関連イベント期間等におけるテロに関する注意喚起</title>
        <lead>●宗教に関連した祝祭日やイベントでは、人の集まりや移動が増えるため、テロの標的とされる可能性が高まります。 
●４月１日（水）から約１週間、ユダヤ教の過越祭（ペサハ）が予定されているほか、４月５日（日）にはカトリックの復活祭（イースター）、４月１２日（日）には東方正教会の復活祭（イースター）が予定されています。  
●常に最新情報の入手に努め、安全確保に十分注意を払ってください。</lead>
        <infoUrl>https://www.anzen.mofa.go.jp/od/ryojiMailDetail.html?keyCd=164069</infoUrl>
        <xmlAllUrl>https://www.ezairyu.mofa.go.jp/opendata/mail/164069A.xml</xmlAllUrl>
        <xmlNormalUrl>https://www.ezairyu.mofa.go.jp/opendata/mail/164069.xml</xmlNormalUrl>
        <xmlLightUrl>https://www.ezairyu.mofa.go.jp/opendata/mail/164069L.xml</xmlLightUrl>
        <koukanCd>502A</koukanCd>
    </mail>
    <mail>
        <keyCd>164068</keyCd>
        <infoType>R10</infoType>
        <leaveDate>2026/04/01 23:50:40</leaveDate>
        <area>
            <cd>42</cd>
        </area>
        <country areaCd="42">
            <cd>0355</cd>
        </country>
        <title>（注意喚起）宗教関連イベント期間等におけるテロに関する注意喚起</title>
        <lead>〇４月１日（水）から約１週間、ユダヤ教の過越祭（ペサハ）が予定されているほか、４月５日（日）にはキリスト教の復活祭（イースター）が予定されています。
〇宗教に関連した祝祭日やイベントでは、人の集まりや移動が増えるため、テロの標的とされる可能性が高まります。特に現在、中東情勢が悪化しており、中東地域以外でも、不測の事態が発生する可能性は排除されません。
〇常に最新情報の入手に努め、安全確保に十分注意を払ってください。

　万が一、事件・事故等に巻き込まれた場合、アルバニア警察当局に被害届を提出するとともに、その概要を在アルバニア日本国大使館に連絡して下さい。

【問い合わせ先】
在アルバニア日本国大使館
電話　： +355 4 454 7930（領事窓口受付時間：09:00～12:00,13:30～16:00（祝休日除く））
メール： konsullore@av.mofa.go.jp
※このメールは在留届、たびレジに登録されたメールアドレスに配信されております。
※「たびレジ」簡易登録をされた方で、メールの配信を変更・停止されたい場合は、以下の URL から停止手続きをお願いいたします。
https://www.ezairyu.mofa.go.jp/tabireg/simple/delete
※災害や騒乱等が発生した際、ご家族、ご友人、同僚を守るため、一人でも多くの方に安全対策に関する情報が届くよう、在留届（3か月以上の滞在）の届出、又はたびレジ（3か月未満の滞在）の登録を、お知り合いの方や出張者・旅行者にご案内いただけますようお願いいたします。</lead>
        <infoUrl>https://www.anzen.mofa.go.jp/od/ryojiMailDetail.html?keyCd=164068</infoUrl>
        <xmlAllUrl>https://www.ezairyu.mofa.go.jp/opendata/mail/164068A.xml</xmlAllUrl>
        <xmlNormalUrl>https://www.ezairyu.mofa.go.jp/opendata/mail/164068.xml</xmlNormalUrl>
        <xmlLightUrl>https://www.ezairyu.mofa.go.jp/opendata/mail/164068L.xml</xmlLightUrl>
        <koukanCd>552A</koukanCd>
    </mail>
    <mail>
        <keyCd>164066</keyCd>
        <infoType>R10</infoType>
        <leaveDate>2026/04/01 23:35:41</leaveDate>
        <area>
            <cd>60</cd>
        </area>
        <country areaCd="60">
            <cd>0260</cd>
        </country>
        <title>【注意喚起】ルサカ市内のデモの発生等（注意を要する場所等）について</title>
        <lead>○４月１日１５時現在、ルサカ市内のザンビア大学周辺及び同大学構内にて発生していた抗議デモは沈静化しました。 
○一方、今後も同大学周辺における予測不能なデモ発生の可能性があります。
○邦人の皆様におかれましては、以下の場所に不用意に近づくことは避けると共に引き続き安全確保に十分ご留意ください。事件・事故に遭遇された場合や不審な点に気づかれた場合は、直ちに警察（緊急電話番号：991または999）へご連絡いただくとともに、当館（電話：＋260-211-251-555）にもご一報くださいますようお願いいたします。</lead>
        <infoUrl>https://www.anzen.mofa.go.jp/od/ryojiMailDetail.html?keyCd=164066</infoUrl>
        <xmlAllUrl>https://www.ezairyu.mofa.go.jp/opendata/mail/164066A.xml</xmlAllUrl>
        <xmlNormalUrl>https://www.ezairyu.mofa.go.jp/opendata/mail/164066.xml</xmlNormalUrl>
        <xmlLightUrl>https://www.ezairyu.mofa.go.jp/opendata/mail/164066L.xml</xmlLightUrl>
        <koukanCd>725A</koukanCd>
    </mail>
    <mail>
        <keyCd>164065</keyCd>
        <infoType>R10</infoType>
        <leaveDate>2026/04/01 23:15:41</leaveDate>
        <area>
            <cd>50</cd>
        </area>
        <country areaCd="50">
            <cd>0966</cd>
        </country>
        <title>イラン関連情報第８報：米国関連企業に対する脅威情報</title>
        <lead>１　３月３１日夜、イランの革命防衛隊系メディアは、これまでの米・イスラエルによるイラン国民を標的とした攻撃において米国のICT及びAI企業が関与しているとして、以下18社を正当な標的とするなどと警告しました。
対象企業：(1)Cisco, (2)HP, (3)Intel, (4)Oracle, (5)Microsoft, (6)Apple, (7)Google, (8)Meta, (9)IBM, (10)DELL, (11)Palantir, (12)Nvidia,(13)J.P.Morgan, (14)Tesla, (15)General Electric, (16)Spire Solutions,(17)Group 42, (18)Boeing
２　さらに、上記企業周辺の住民に対して、半径１キロメートル以内の場所から避難するよう警告するとともに、今後イラン国内で暗殺行為が発生した場合、４月１日午後８時（テヘラン時間）以降、上記企業が攻撃されることを覚悟するよう警告しました。
３　これを受けて同日、在サウジアラビア米国大使館は、セキュリティ・アラートを以下のとおり更新しています。
－ 米国市民が集まる場所に対する脅迫の報告をフォローしています。米国市民の皆様には、ホテル、その他米国内の企業や教育機関を含む集会場所が標的となる可能性があることにご留意ください。
https://sa.usembassy.gov/security-alert-u-s-embassy-riyadh-saudi-arabia-march-31-2026/
４　在留邦人の皆様におかれましては、引き続き、
－ 攻撃の対象となる可能性のある施設には近づかない（写真撮影も厳禁）
－ ミサイル・ドローン、着弾状況等の写真撮影、SNSへの投稿・共有を行わない
－ 信頼できる公式の情報源からの最新情報を確認する
などして、ご自身の安全確保に努めてください。
　　万が一、被害に遭われた場合や邦人の被害情報に接した場合には、総領事館まですぐにお知らせください。</lead>
        <infoUrl>https://www.anzen.mofa.go.jp/od/ryojiMailDetail.html?keyCd=164065</infoUrl>
        <xmlAllUrl>https://www.ezairyu.mofa.go.jp/opendata/mail/164065A.xml</xmlAllUrl>
        <xmlNormalUrl>https://www.ezairyu.mofa.go.jp/opendata/mail/164065.xml</xmlNormalUrl>
        <xmlLightUrl>https://www.ezairyu.mofa.go.jp/opendata/mail/164065L.xml</xmlLightUrl>
        <koukanCd>708D</koukanCd>
    </mail>
    <mail>
        <keyCd>164062</keyCd>
        <infoType>R10</infoType>
        <leaveDate>2026/04/01 22:25:40</leaveDate>
        <area>
            <cd>42</cd>
        </area>
        <country areaCd="42">
            <cd>0030</cd>
        </country>
        <title>悪天候ERMINIOに関する注意喚起</title>
        <lead>○ギリシャ気象庁は、本日1日（水）から明日2日（木）にかけて、アッティカ県を含むほぼ全国での大雨や豪雨、強風のほか、山間部では降雪を予想し、最も高い警戒レベルである「赤」を発令しました（4段階の警戒レベルの4）。
○ギリシャ気候危機・市民防災省は、悪天候に対する以下の予防措置を呼びかけています。
・テレビ、ラジオ等で最新情報を入手し、当局の指示に従う。
・悪天候時には、不要不急の外出を控える。
・海域や沿岸部での活動は避ける。
・氾濫した沢や道路は、車でも徒歩でも横断しないこと。
・強風時は、大きな木や標識等、倒れたり落下する危険性のあるものに近づかない。また、その下に駐車しない。
・一部地域では、車のタイヤチェーン（降雪時は装着）の搭載など、滑り止め対策が義務付けられ、搭載していない場合は違反金が科せられることがある。
・危険な時は、「112番」（緊急サービスに繋がる欧州共通緊急番号）または「100番」（警察）、「199番」（消防庁）、「166番」（救急救命）に連絡する。
○ギリシャに滞在中の方は、報道や以下のサイトで最新の気象情報を確認し、悪天候時には不要不急の外出を控えるなど、身の安全の確保に努めてください。

・ギリシャ気候危機・市民防災省
https://civilprotection.gov.gr/
https://civilprotection.gov.gr/odigies-prostasias?lang=en（安全対策）
・ギリシャ気象庁
https://emy.gr/en/warnings?tab=mainland&amp;area=current-alerts</lead>
        <infoUrl>https://www.anzen.mofa.go.jp/od/ryojiMailDetail.html?keyCd=164062</infoUrl>
        <xmlAllUrl>https://www.ezairyu.mofa.go.jp/opendata/mail/164062A.xml</xmlAllUrl>
        <xmlNormalUrl>https://www.ezairyu.mofa.go.jp/opendata/mail/164062.xml</xmlNormalUrl>
        <xmlLightUrl>https://www.ezairyu.mofa.go.jp/opendata/mail/164062L.xml</xmlLightUrl>
        <koukanCd>507A</koukanCd>
    </mail>
    <mail>
        <keyCd>164061</keyCd>
        <infoType>R10</infoType>
        <leaveDate>2026/04/01 22:10:40</leaveDate>
        <area>
            <cd>50</cd>
        </area>
        <country areaCd="50">
            <cd>0964</cd>
        </country>
        <title>イラク国内の状況及び注意喚起（４月１日）</title>
        <lead>１　当地米国大使館は、引き続きセキュリティアラートを発出しており、イラクからの早期退避を含めた注意喚起を行っています。以下ウェブサイトの言及のとおり、これまでにスレイマーニーヤ県（クルディスタン地域）の米系大学を標的とした可能性のある攻撃があった他、昨日は米国人ジャーナリストの誘拐事案が報じられています。
https://iq.usembassy.gov/security-alert-u-s-embassy-baghdad-iraq-march-29-2026/

２　また、バグダッドやエルビル等の都市部も含め爆発物を使用した事案が連日継続的に発生しています。さらに今週４日（土）には、当地の宗教指導者であるサドル師の呼びかけで反米・イスラエルを訴える集会が各地で予定されています。

３　現在も、イラク空域封鎖は継続されており、航空便の再開のめどはたっていませんが、トルコ、クウェート等の陸路国境は開放されています。特にイラクからトルコへ入国に際しては、以下の情報の事前通報が必要となっており、他のルートについても今後、類似の措置がとられる可能性がありますので、万一現在もイラク滞在をされている場合は、当館又はエルビル領事事務所に必要情報の連絡の上、早期の出国※をお願いします。

（陸路でのイラク出国に必要な情報）
●　出国日
●　パスポート情報（顔写真ページ写し）
●　出国先での一時滞在先
●　出国先からの航空券情報（Eチケット写し）

※現在、イラク全域は危険情報がレベル４（退避勧告）となっています。
https://www.anzen.mofa.go.jp/info/pchazardspecificinfo_2026T036.html#ad-image-0</lead>
        <infoUrl>https://www.anzen.mofa.go.jp/od/ryojiMailDetail.html?keyCd=164061</infoUrl>
        <xmlAllUrl>https://www.ezairyu.mofa.go.jp/opendata/mail/164061A.xml</xmlAllUrl>
        <xmlNormalUrl>https://www.ezairyu.mofa.go.jp/opendata/mail/164061.xml</xmlNormalUrl>
        <xmlLightUrl>https://www.ezairyu.mofa.go.jp/opendata/mail/164061L.xml</xmlLightUrl>
        <koukanCd>704A</koukanCd>
    </mail>
    <mail>
        <keyCd>164060</keyCd>
        <infoType>R10</infoType>
        <leaveDate>2026/04/01 22:00:42</leaveDate>
        <area>
            <cd>60</cd>
        </area>
        <country areaCd="60">
            <cd>0027</cd>
        </country>
        <title>強盗事件の発生（ヨハネスブルグＣＢＤ（Central Business District））</title>
        <lead>南アフリカにお住まいの皆様及び旅行者の皆様へ

【ポイント】
３月３１日、邦人旅行者が首締め強盗に遭い、財布、スマートフォンを強奪される事件が発生しました。</lead>
        <infoUrl>https://www.anzen.mofa.go.jp/od/ryojiMailDetail.html?keyCd=164060</infoUrl>
        <xmlAllUrl>https://www.ezairyu.mofa.go.jp/opendata/mail/164060A.xml</xmlAllUrl>
        <xmlNormalUrl>https://www.ezairyu.mofa.go.jp/opendata/mail/164060.xml</xmlNormalUrl>
        <xmlLightUrl>https://www.ezairyu.mofa.go.jp/opendata/mail/164060L.xml</xmlLightUrl>
        <koukanCd>718A</koukanCd>
    </mail>
    <mail>
        <keyCd>164059</keyCd>
        <infoType>R10</infoType>
        <leaveDate>2026/04/01 21:21:22</leaveDate>
        <area>
            <cd>60</cd>
        </area>
        <country areaCd="60">
            <cd>0260</cd>
        </country>
        <title>【注意喚起】ルサカ市内のデモの発生等について</title>
        <lead>○４月１日１３時１７分現在、ルサカ市内のザンビア大学周辺及び同大学構内にて、学生による抗議デモが発生しました。 
○今後も同大学周辺における予測不能なデモ発生の可能性があります。
○邦人の皆様におかれましては、同大学周辺には不用意に近づかないようお願いするとともに、安全確保に十分ご留意ください。万が一被害に遭われた場合には大使館にご一報いただくよう宜しくお願いします。 以下、事案の詳細および注意喚起事項をお伝えします。</lead>
        <infoUrl>https://www.anzen.mofa.go.jp/od/ryojiMailDetail.html?keyCd=164059</infoUrl>
        <xmlAllUrl>https://www.ezairyu.mofa.go.jp/opendata/mail/164059A.xml</xmlAllUrl>
        <xmlNormalUrl>https://www.ezairyu.mofa.go.jp/opendata/mail/164059.xml</xmlNormalUrl>
        <xmlLightUrl>https://www.ezairyu.mofa.go.jp/opendata/mail/164059L.xml</xmlLightUrl>
        <koukanCd>725A</koukanCd>
    </mail>
    <mail>
        <keyCd>164057</keyCd>
        <infoType>R10</infoType>
        <leaveDate>2026/04/01 20:56:04</leaveDate>
        <area>
            <cd>42</cd>
        </area>
        <country areaCd="42">
            <cd>0044</cd>
        </country>
        <title>宗教関連イベント期間等におけるテロに関する注意喚起</title>
        <lead>【ポイント】
●宗教に関連した祝祭日やイベントでは、人の集まりや移動が増えるため、テロの標的とされる可能性が高まります。特に現在、中東情勢の悪化を受け、中東地域以外でも不測の事態が発生する可能性は排除されません。
●４月１日（水）から約１週間、ユダヤ教の過越祭（ペサハ）が予定されているほか、４月５日（日）にはキリスト教の復活祭（イースター）が予定されています。 
●常に最新情報の入手に努め、安全確保に十分注意を払ってください。</lead>
        <infoUrl>https://www.anzen.mofa.go.jp/od/ryojiMailDetail.html?keyCd=164057</infoUrl>
        <xmlAllUrl>https://www.ezairyu.mofa.go.jp/opendata/mail/164057A.xml</xmlAllUrl>
        <xmlNormalUrl>https://www.ezairyu.mofa.go.jp/opendata/mail/164057.xml</xmlNormalUrl>
        <xmlLightUrl>https://www.ezairyu.mofa.go.jp/opendata/mail/164057L.xml</xmlLightUrl>
        <koukanCd>518A</koukanCd>
    </mail>
    <mail>
        <keyCd>164056</keyCd>
        <infoType>R10</infoType>
        <leaveDate>2026/04/01 20:35:40</leaveDate>
        <area>
            <cd>50</cd>
        </area>
        <country areaCd="50">
            <cd>0965</cd>
        </country>
        <title>クウェート国際空港の状況（4月1日14:00時点）について</title>
        <lead>○4月1日（現地時間）、クウェート民間航空局はクウェート国際空港が複数のドローンの標的となり、物的被害が発生した旨発表しました。

○4月1日14:00時点（現地時間）、クウェート国際空港は閉鎖されています。
邦人の皆様におかれましても、関連情報の入手に努めるようお願いします。

○同空港のサイトを以下のとおりお知らせします。
クウェート国際空港（Kuwait International Airport）
https://www.kuwaitairport.gov.kw/en/　
※	クウェート発着便の運行状況について確認できます。


在クウェート日本国大使館
当館公式サイト： https://www.kw.emb-japan.go.jp/itprtop_ja/index.html
メールアドレス： consular@kw.mofa.go.jp 
電話：（+965）2530-9400

※「在留届」を提出された方で、既に日本に帰国又は他国に転出された方は、以下のURLから「変更届・帰国届」の提出をお願いいたします。
（ https://www.ezairyu.mofa.go.jp/RRnet/index.html ）
※「たびレジ」簡易登録をされた方でメールの配信を停止したい方は、以下のURLから停止手続きをお願い致します。
（ https://www.ezairyu.mofa.go.jp/tabireg/simple/delete ）
※このメールは在留届、たびレジに登録されたメールアドレスに配信されております。
災害や騒乱等が発生した際、ご家族、ご友人、同僚の方を守るため、一人でも多くの方に安全対策に関する情報が届くよう、「在留届」（３か月以上の滞在）または「たびレジ」（３か月未満の滞在）の登録を、お知り合いの方や出張者、旅行者の方にご案内いただけますようお願いいたします。</lead>
        <infoUrl>https://www.anzen.mofa.go.jp/od/ryojiMailDetail.html?keyCd=164056</infoUrl>
        <xmlAllUrl>https://www.ezairyu.mofa.go.jp/opendata/mail/164056A.xml</xmlAllUrl>
        <xmlNormalUrl>https://www.ezairyu.mofa.go.jp/opendata/mail/164056.xml</xmlNormalUrl>
        <xmlLightUrl>https://www.ezairyu.mofa.go.jp/opendata/mail/164056L.xml</xmlLightUrl>
        <koukanCd>706A</koukanCd>
    </mail>
    <mail>
        <keyCd>164055</keyCd>
        <infoType>R10</infoType>
        <leaveDate>2026/04/01 20:15:41</leaveDate>
        <area>
            <cd>42</cd>
        </area>
        <country areaCd="42">
            <cd>0359</cd>
        </country>
        <title>宗教関連イベント期間等におけるテロに関する注意喚起</title>
        <lead>【ポイント】
●宗教に関連した祝祭日やイベントでは、人の集まりや移動が増えるため、テロの標的とされる可能性が高まります。 
●４月１日（水）から約１週間、ユダヤ教の過越祭（ペサハ）が予定されているほか、４月５日（日）にはカトリックの復活祭（イースター）、４月１２日（日）には東方正教会の復活祭（イースター）が予定されています。  
●常に最新情報の入手に努め、安全確保に十分注意を払ってください。</lead>
        <infoUrl>https://www.anzen.mofa.go.jp/od/ryojiMailDetail.html?keyCd=164055</infoUrl>
        <xmlAllUrl>https://www.ezairyu.mofa.go.jp/opendata/mail/164055A.xml</xmlAllUrl>
        <xmlNormalUrl>https://www.ezairyu.mofa.go.jp/opendata/mail/164055.xml</xmlNormalUrl>
        <xmlLightUrl>https://www.ezairyu.mofa.go.jp/opendata/mail/164055L.xml</xmlLightUrl>
        <koukanCd>524A</koukanCd>
    </mail>
    <mail>
        <keyCd>164054</keyCd>
        <infoType>R10</infoType>
        <leaveDate>2026/04/01 19:35:41</leaveDate>
        <area>
            <cd>50</cd>
        </area>
        <country areaCd="50">
            <cd>0966</cd>
        </country>
        <title>イラン関連情報第１８報：米国関連企業に対する脅威情報</title>
        <lead>１　３月３１日夜、イランの革命防衛隊系メディアは、これまでの米・イスラエルによるイラン国民を標的とした攻撃において米国のICT及びAI企業が関与しているとして、以下18社を正当な標的とするなどと警告しました。
対象企業：(1)Cisco, (2)HP, (3)Intel, (4)Oracle, (5)Microsoft, (6)Apple, (7)Google, (8)Meta, (9)IBM, (10)DELL, (11)Palantir, (12)Nvidia,(13)J.P.Morgan, (14)Tesla, (15)General Electric, (16)Spire Solutions,(17)Group 42, (18)Boeing

２　さらに、上記企業周辺の住民に対して、半径１キロメートル以内の場所から避難するよう警告するとともに、今後イラン国内で暗殺行為が発生した場合、４月１日午後８時（テヘラン時間）以降、上記企業が攻撃されることを覚悟するよう警告しました。

３　これを受けて同日、在サウジアラビア米国大使館は、セキュリティ・アラートを以下のとおり更新しています。
－ 米国市民が集まる場所に対する脅迫の報告をフォローしています。米国市民の皆様には、ホテル、その他米国内の企業や教育機関を含む集会場所が標的となる可能性があることにご留意ください。
https://sa.usembassy.gov/security-alert-u-s-embassy-riyadh-saudi-arabia-march-31-2026/

４　在留邦人の皆様におかれましては、引き続き、
－ 攻撃の対象となる可能性のある施設には近づかない（写真撮影も厳禁）
－ ミサイル・ドローン、着弾状況等の写真撮影、SNSへの投稿・共有を行わない
－ 信頼できる公式の情報源からの最新情報を確認する
などして、ご自身の安全確保に努めてください。
　　万が一、被害に遭われた場合や邦人の被害情報に接した場合には、大使館まですぐにお知らせください。</lead>
        <infoUrl>https://www.anzen.mofa.go.jp/od/ryojiMailDetail.html?keyCd=164054</infoUrl>
        <xmlAllUrl>https://www.ezairyu.mofa.go.jp/opendata/mail/164054A.xml</xmlAllUrl>
        <xmlNormalUrl>https://www.ezairyu.mofa.go.jp/opendata/mail/164054.xml</xmlNormalUrl>
        <xmlLightUrl>https://www.ezairyu.mofa.go.jp/opendata/mail/164054L.xml</xmlLightUrl>
        <koukanCd>708A</koukanCd>
    </mail>
    <mail>
        <keyCd>164053</keyCd>
        <infoType>R10</infoType>
        <leaveDate>2026/04/01 19:20:40</leaveDate>
        <area>
            <cd>50</cd>
        </area>
        <country areaCd="50">
            <cd>0973</cd>
        </country>
        <title>米国関連企業への脅威情報(４月１日）</title>
        <lead>１．3月31日(現地時間)、イランのイスラム革命防衛隊（IRGC）関連のテレグラム（SNS）において、「イランへの攻撃において主要な役割を果たしている米国のICT及びAI企業を標的にする。」「地域内の関連企業の従業員及び周辺住民は半径１キロメートル以内から離れること。」「現地時間の4月1日午後8時（バーレーン時間午後7時30分）以降、イラン国内への攻撃が発生する度に、当該企業は攻撃され得る。」旨の内容を投稿し、関連企業としてCisco、Oracle、Microsoft、GP.Morgan等18の企業を名指しました。
（関連リンク：ペルシャ語）：https://t.me/sepahpasdaran/20555 
２．これら企業は、World Trade CenterやFinancial Harbourが所在するManama地区北部やSeef地区等に所在しているとの情報もあることから、本声明内容を踏まえ、当面の間、関連する可能性のある施設及びその近傍施設への不要不急の立ち寄りは避けるようにしてください。
３．また、ドローンやミサイル等に起因すると思われる爆発音等が聞こえた場合は、決して近づくことなく、
　　屋外にいる場合：近くの建物や地下への避難、物陰に身を隠す
　　屋内にいる場合：窓から離れる、窓のない部屋に移動する
といった、ご自身の身を守る行動を最優先に行うようお願いします。</lead>
        <infoUrl>https://www.anzen.mofa.go.jp/od/ryojiMailDetail.html?keyCd=164053</infoUrl>
        <xmlAllUrl>https://www.ezairyu.mofa.go.jp/opendata/mail/164053A.xml</xmlAllUrl>
        <xmlNormalUrl>https://www.ezairyu.mofa.go.jp/opendata/mail/164053.xml</xmlNormalUrl>
        <xmlLightUrl>https://www.ezairyu.mofa.go.jp/opendata/mail/164053L.xml</xmlLightUrl>
        <koukanCd>727A</koukanCd>
    </mail>
    <mail>
        <keyCd>164052</keyCd>
        <infoType>R10</infoType>
        <leaveDate>2026/04/01 19:10:40</leaveDate>
        <area>
            <cd>10</cd>
        </area>
        <country areaCd="10">
            <cd>0091</cd>
        </country>
        <title>西ベンガル州議会総選挙期間中の注意喚起</title>
        <lead>＜ポイント＞
●西ベンガル州では、西ベンガル州議会総選挙が、４月２３日と４月２９日の２段階で実施されます。
●５月４日の開票・結果発表までの間は、各地で選挙運動の加熱化や政党間支持者の衝突、投票妨害等不測の事態が発生する恐れは排除できませんので、選挙関連の現場にはできるかぎり近づかず、やむを得ない場合も十分に注意してください。</lead>
        <infoUrl>https://www.anzen.mofa.go.jp/od/ryojiMailDetail.html?keyCd=164052</infoUrl>
        <xmlAllUrl>https://www.ezairyu.mofa.go.jp/opendata/mail/164052A.xml</xmlAllUrl>
        <xmlNormalUrl>https://www.ezairyu.mofa.go.jp/opendata/mail/164052.xml</xmlNormalUrl>
        <xmlLightUrl>https://www.ezairyu.mofa.go.jp/opendata/mail/164052L.xml</xmlLightUrl>
        <koukanCd>606E</koukanCd>
    </mail>
    <mail>
        <keyCd>164051</keyCd>
        <infoType>R10</infoType>
        <leaveDate>2026/04/01 19:05:44</leaveDate>
        <area>
            <cd>42</cd>
        </area>
        <country areaCd="42">
            <cd>0041</cd>
        </country>
        <title>宗教関連イベントにおけるテロに関する注意喚起</title>
        <lead>●宗教に関連した祝祭日やイベントでは、人の集まりや移動が増えるため、無差別テロに遭遇する可能性が高まります。特に現在、中東情勢が悪化しており、中東地域以外でも、不測の事態が発生する可能性は排除されません。  
●４月１日（水）から約１週間、ユダヤ教の過越祭（ペサハ）が予定されているほか、４月５日（日）にはキリスト教の復活祭（イースター）が予定されています。  
●常に最新情報の入手に努め、安全確保に十分注意を払ってください。</lead>
        <infoUrl>https://www.anzen.mofa.go.jp/od/ryojiMailDetail.html?keyCd=164051</infoUrl>
        <xmlAllUrl>https://www.ezairyu.mofa.go.jp/opendata/mail/164051A.xml</xmlAllUrl>
        <xmlNormalUrl>https://www.ezairyu.mofa.go.jp/opendata/mail/164051.xml</xmlNormalUrl>
        <xmlLightUrl>https://www.ezairyu.mofa.go.jp/opendata/mail/164051L.xml</xmlLightUrl>
        <koukanCd>516A</koukanCd>
    </mail>
    <mail>
        <keyCd>164050</keyCd>
        <infoType>R10</infoType>
        <leaveDate>2026/04/01 18:50:41</leaveDate>
        <area>
            <cd>42</cd>
        </area>
        <country areaCd="42">
            <cd>0353</cd>
        </country>
        <title>【安全情報】宗教関連イベント期間等におけるテロに関する注意喚起</title>
        <lead>○宗教に関連した祝祭日やイベントでは、人の集まりや移動が増えるため、テロの標的とされる可能性が高まります。特に現在、中東情勢が悪化しており、中東地域以外でも、不測の事態が発生する可能性は排除されません。 

○4月1日（水）から約１週間、ユダヤ教の過越祭（ペサハ）が予定されているほか、4月5日（日）にはキリスト教の復活祭（イースター）が予定されています。</lead>
        <infoUrl>https://www.anzen.mofa.go.jp/od/ryojiMailDetail.html?keyCd=164050</infoUrl>
        <xmlAllUrl>https://www.ezairyu.mofa.go.jp/opendata/mail/164050A.xml</xmlAllUrl>
        <xmlNormalUrl>https://www.ezairyu.mofa.go.jp/opendata/mail/164050.xml</xmlNormalUrl>
        <xmlLightUrl>https://www.ezairyu.mofa.go.jp/opendata/mail/164050L.xml</xmlLightUrl>
        <koukanCd>522A</koukanCd>
    </mail>
    <mail>
        <keyCd>164049</keyCd>
        <infoType>R10</infoType>
        <leaveDate>2026/04/01 18:35:45</leaveDate>
        <area>
            <cd>10</cd>
        </area>
        <country areaCd="10">
            <cd>0886</cd>
        </country>
        <title>清明節等期間中の閉所日及び安全対策に関するお知らせ</title>
        <lead>●台湾の清明節等の祝日に合わせ、当協会台北事務所及び高雄事務所は、４月３日（金）から４月６日（月）まで閉所となります。４月７日（火）より開所します。
●清明節期間中は、多くの人が移動し、特に観光地等は大勢の人が集まることが見込まれます。貴重品・旅券（パスポート）等の管理含め、外出の際には周囲の状況にくれぐれも留意し、可能な限りの安全対策に努めてください。また、渡航にあたっては、十分な補償内容の海外旅行保険等に加入することを強く推奨します。
●出入境時の持ち出し・持ち込みに制限のある物品もありますので、ご留意ください。また、感染症にご注意ください。</lead>
        <infoUrl>https://www.anzen.mofa.go.jp/od/ryojiMailDetail.html?keyCd=164049</infoUrl>
        <xmlAllUrl>https://www.ezairyu.mofa.go.jp/opendata/mail/164049A.xml</xmlAllUrl>
        <xmlNormalUrl>https://www.ezairyu.mofa.go.jp/opendata/mail/164049.xml</xmlNormalUrl>
        <xmlLightUrl>https://www.ezairyu.mofa.go.jp/opendata/mail/164049L.xml</xmlLightUrl>
        <koukanCd>632A</koukanCd>
    </mail>
    <mail>
        <keyCd>164048</keyCd>
        <infoType>R10</infoType>
        <leaveDate>2026/04/01 18:20:41</leaveDate>
        <area>
            <cd>42</cd>
        </area>
        <country areaCd="42">
            <cd>0352</cd>
        </country>
        <title>宗教関連イベント期間等におけるテロに関する注意喚起</title>
        <lead>●宗教に関連した祝祭日やイベントでは、人の集まりや移動が増えるため、テロの標的とされる可能性が高まります。特に現在、中東情勢が悪化しており、中東地域以外でも、不測の事態が発生する可能性は排除されません。
●４月１日（水）から約１週間、ユダヤ教の過越祭（ペサハ）が予定されているほか、４月５日（日）にはキリスト教の復活祭（イースター）が予定されています。 
●常に最新情報の入手に努め、安全確保に十分注意を払ってください。</lead>
        <infoUrl>https://www.anzen.mofa.go.jp/od/ryojiMailDetail.html?keyCd=164048</infoUrl>
        <xmlAllUrl>https://www.ezairyu.mofa.go.jp/opendata/mail/164048A.xml</xmlAllUrl>
        <xmlNormalUrl>https://www.ezairyu.mofa.go.jp/opendata/mail/164048.xml</xmlNormalUrl>
        <xmlLightUrl>https://www.ezairyu.mofa.go.jp/opendata/mail/164048L.xml</xmlLightUrl>
        <koukanCd>526A</koukanCd>
    </mail>
    <mail>
        <keyCd>164047</keyCd>
        <infoType>R10</infoType>
        <leaveDate>2026/04/01 18:05:40</leaveDate>
        <area>
            <cd>42</cd>
        </area>
        <country areaCd="42">
            <cd>0049</cd>
        </country>
        <title>【安全情報】宗教関連イベント期間等におけるテロに関する注意喚起</title>
        <lead>●宗教に関連した祝祭日やイベントでは、人の集まりや移動が増えるため、テロの標的とされる可能性が高まります。特に現在、中東情勢が悪化しており、中東地域以外でも、不測の事態が発生する可能性は排除されません。
●４月１日（水）から約１週間、ユダヤ教の過越祭（ペサハ）が予定されているほか、４月５日（日）にはキリスト教の復活祭（イースター）が予定されています。
●常に最新情報の入手に努め、安全確保に十分注意を払ってください。</lead>
        <infoUrl>https://www.anzen.mofa.go.jp/od/ryojiMailDetail.html?keyCd=164047</infoUrl>
        <xmlAllUrl>https://www.ezairyu.mofa.go.jp/opendata/mail/164047A.xml</xmlAllUrl>
        <xmlNormalUrl>https://www.ezairyu.mofa.go.jp/opendata/mail/164047.xml</xmlNormalUrl>
        <xmlLightUrl>https://www.ezairyu.mofa.go.jp/opendata/mail/164047L.xml</xmlLightUrl>
        <koukanCd>506E</koukanCd>
    </mail>
    <mail>
        <keyCd>164046</keyCd>
        <infoType>R10</infoType>
        <leaveDate>2026/04/01 18:00:44</leaveDate>
        <area>
            <cd>50</cd>
        </area>
        <country areaCd="50">
            <cd>0972</cd>
        </country>
        <country areaCd="50">
            <cd>0970</cd>
        </country>
        <title>テルアビブ（ベン・グリオン）空港等の状況について（4月1日(水)12:00時点）</title>
        <lead>・4月1日(水)12時現在（現地時間）、テルアビブ（ベン・グリオン）空港は、便数・搭乗者数を制限した状態での極めて限定された運用となっています。 
・イスラエル系航空会社のみによる特別運航（Recovery/Rescue/Emergency Flight）が継続しています。
・3月23日(月)17時から、１時間あたり出発機１機、到着機１機の制限及びイスラエル出発便搭乗可能人数が50人となっています。
・エル・アルの定期便は、4月11日(土)までキャンセルされています。

==============================
◆イラン、ヒズボッラーからのミサイル等に 
　よる攻撃が継続しています。  
◆在留邦人・渡航者の方で、負傷等の被害に 
　遭われた方や被害の情報に接した方がいらっ
　しゃいましたら、下記の当館連絡先まで 
　ご連絡をお願いします。 
==============================

▲▼▲▼▲▼新着情報▲▼▲▼▲▼ 

■■ベン・グリオン空港運航状況 
●公式ウェブページ（出発便情報） 
https://www.iaa.gov.il/en/airports/ben-gurion/flight-board/?flightType=departures　
※掲載されているのは4月5日(日)まで（昨日と変わらず）。

●4月1日(水)出発便フライト予定（24便）
AIR HAIFA&lt;3&gt;
----LARNACA 3
ARKIA ISRAELI AIRLINES&lt;4&gt;
----ATHENS 2
----LARNACA 1
----LARNACA via BANGKOK 1
EL AL ISRAEL AIRLINES&lt;12&gt;
----ATHENS 3
----LONDON 1
----NEWARK 1
----PARIS 2
----ROME 3
----LOS ANGELES 1
----NEW YORK 1
ISRAIR AIRLINES&lt;5&gt;
----ATHENS 1
----LARNACA 2
----ROME 1
----BUDAPEST 1</lead>
        <infoUrl>https://www.anzen.mofa.go.jp/od/ryojiMailDetail.html?keyCd=164046</infoUrl>
        <xmlAllUrl>https://www.ezairyu.mofa.go.jp/opendata/mail/164046A.xml</xmlAllUrl>
        <xmlNormalUrl>https://www.ezairyu.mofa.go.jp/opendata/mail/164046.xml</xmlNormalUrl>
        <xmlLightUrl>https://www.ezairyu.mofa.go.jp/opendata/mail/164046L.xml</xmlLightUrl>
        <koukanCd>705A</koukanCd>
    </mail>
    <mail>
        <keyCd>164045</keyCd>
        <infoType>R10</infoType>
        <leaveDate>2026/04/01 17:50:40</leaveDate>
        <area>
            <cd>42</cd>
        </area>
        <country areaCd="42">
            <cd>0040</cd>
        </country>
        <title>宗教関連イベント期間等におけるテロに関する注意喚起</title>
        <lead>●宗教に関連した祝祭日やイベントでは、人の集まりや移動が増えるため、テロの標的とされる可能性が高まります。特に現在、中東情勢が悪化しており、中東地域以外でも、不測の事態が発生する可能性は排除されません。

●４月１日（水）から約１週間、ユダヤ教の過越祭（ペサハ）が予定されているほか、４月５日（日）にはキリスト教（西方教会）の復活祭イースターが予定されています。（ルーマニア正教のイースターは4月12日）

●常に最新情報の入手に努め、安全確保に十分注意を払ってください。</lead>
        <infoUrl>https://www.anzen.mofa.go.jp/od/ryojiMailDetail.html?keyCd=164045</infoUrl>
        <xmlAllUrl>https://www.ezairyu.mofa.go.jp/opendata/mail/164045A.xml</xmlAllUrl>
        <xmlNormalUrl>https://www.ezairyu.mofa.go.jp/opendata/mail/164045.xml</xmlNormalUrl>
        <xmlLightUrl>https://www.ezairyu.mofa.go.jp/opendata/mail/164045L.xml</xmlLightUrl>
        <koukanCd>523A</koukanCd>
    </mail>
    <mail>
        <keyCd>164044</keyCd>
        <infoType>R10</infoType>
        <leaveDate>2026/04/01 16:40:48</leaveDate>
        <area>
            <cd>42</cd>
        </area>
        <country areaCd="42">
            <cd>0031</cd>
        </country>
        <title>【安全情報】宗教関連イベント期間等におけるテロに関する注意喚起</title>
        <lead>●宗教に関連した祝祭日やイベントでは、人の集まりや移動が増えるため、テロの標的とされる可能性が高まります。特に現在、中東情勢が悪化しており、中東地域以外でも、不測の事態が発生する可能性は排除されません。
●４月１日（水）から約１週間、ユダヤ教の過越祭（ペサハ）が予定されているほか、４月５日（日）にはキリスト教の復活祭（イースター）が予定されています。
●常に最新情報の入手に努め、安全確保に十分注意を払ってください。</lead>
        <infoUrl>https://www.anzen.mofa.go.jp/od/ryojiMailDetail.html?keyCd=164044</infoUrl>
        <xmlAllUrl>https://www.ezairyu.mofa.go.jp/opendata/mail/164044A.xml</xmlAllUrl>
        <xmlNormalUrl>https://www.ezairyu.mofa.go.jp/opendata/mail/164044.xml</xmlNormalUrl>
        <xmlLightUrl>https://www.ezairyu.mofa.go.jp/opendata/mail/164044L.xml</xmlLightUrl>
        <koukanCd>510A</koukanCd>
    </mail>
</opendata>
